[{"id":"colorful_quinoa_in_baked_delorit","title":"קינואה ססגונית בדלורית אפויה","preparationTime":"שעה","category":"מקצועניים, חובבנים ומשפחתי","amount":"6 חצאי דלורית ממולאים","rank":"","remark":"קינואה היא דגן-על העשיר בחלבון איכותי","ingredients":"דלוריות, קינואה לבנה, קינואה אדומה, שעועית מאש, בצל, פטרוזיליה, שום, שמן זית, מיץ לימון, מלח, פלפל שחור","instructions":"אופים את הדלוריות, בוררים ומשרים את הקינואה והשעועית, מבשלים בנפרד, מערבבים עם בצל, פטרוזיליה, שום, מיץ לימון ושמן זית, מסדרים בתוך הדלוריות"}]